langgraph_checkpointer_couchbase/__init__.py
langgraph_checkpointer_couchbase/async_cb_saver.py
langgraph_checkpointer_couchbase/couchbase_saver.py
langgraph_checkpointer_couchbase/utils.py
langgraph_checkpointer_couchbase-1.0.8.dist-info/METADATA
langgraph_checkpointer_couchbase-1.0.8.dist-info/WHEEL
langgraph_checkpointer_couchbase-1.0.8.dist-info/licenses/LICENSE
langgraph_checkpointer_couchbase-1.0.8.dist-info/RECORD
