Metadata-Version: 2.4
Name: langgraph-checkpointer-couchbase
Version: 1.0.8
Project-URL: Documentation, https://github.com/couchbase-ecosystem/langgraph-checkpointer-couchbase#readme
Project-URL: Issues, https://github.com/couchbase-ecosystem/langgraph-checkpointer-couchbase/issues
Project-URL: Source, https://github.com/couchbase-ecosystem/langgraph-checkpointer-couchbase
Author-email: Lokesh Goel <lokesh.goel@couchbase.com>
License-Expression: MIT
License-File: LICENSE
Keywords: checkpointer,couchbase,langchain,langgraph,persistence
Classifier: Development Status :: 4 - Beta
Classifier: Programming Language :: Python
Classifier: Programming Language :: Python :: 3.8
Classifier: Programming Language :: Python :: 3.9
Classifier: Programming Language :: Python :: 3.10
Classifier: Programming Language :: Python :: 3.11
Classifier: Programming Language :: Python :: 3.12
Classifier: Programming Language :: Python :: Implementation :: CPython
Classifier: Programming Language :: Python :: Implementation :: PyPy
Requires-Python: >=3.8
Requires-Dist: couchbase>=4.5.0
Requires-Dist: langchain-openai>=1.1.3
Requires-Dist: langchain>=1.1.3
Requires-Dist: langgraph>=1.0.5
Requires-Dist: pydantic>=2.12.5
Requires-Dist: python-dotenv>=1.0.0
Requires-Dist: typing-extensions>=4.15.0
